<scene title="Vehicle test" renderFPS="144" updateFPS="60" physicsFPS="360">

    <scene source="scenes/performance/physx_performance_overlay.xml" renderEngine="web" />

    <object id="player">
<!--        <MovementGL _package="pl.AWTGameEngine.custom" />-->
<!--        <MovementFX _package="pl.AWTGameEngine.custom" />-->
        <StateSaverTest _package="pl.AWTGameEngine.custom.performance" />
        <CameraFX />
        <Server port="53780" />
    </object>

    <object id="floor" x="500" y="-100" z="-500" size="1000,10,10000">
        <Box3D spriteSource="hdr_sprites/glass.png" />
        <RigidBody.Static />
    </object>

    <object id="floor2" x="500" y="-100" z="-500" size="100,10,100">
        <Box3D spriteSource="hdr_sprites/glass.png" />
        <RigidBody.Static />
    </object>

    <object id="box0" x="30" y="-80" z="0" size="10,10,10">
        <Box3D spriteSource="sprites/beaver.jpg" />
        <RigidBody.Dynamic />
    </object>
    <object id="box1" x="30" y="-60" z="0" size="10,10,10">
        <Box3D spriteSource="sprites/beaver.jpg" />
        <RigidBody.Dynamic />
        <Joint.Revolute reference="box0" />
    </object>
    <object id="box2" x="0" y="-80" z="30" size="10,10,10">
        <Box3D spriteSource="sprites/beaver.jpg" />
        <RigidBody.Dynamic />
    </object>
    <object id="box3" x="0" y="-60" z="30" size="10,10,10">
        <Box3D spriteSource="sprites/beaver.jpg" />
        <RigidBody.Dynamic />
    </object>

    <object id="box4" x="30" y="-80" z="30" size="10,10,10">
        <Box3D spriteSource="sprites/beaver.jpg" />
        <RigidBody.Dynamic />
    </object>
    <object id="box5" x="30" y="-60" z="30" size="10,10,10">
        <Box3D spriteSource="sprites/beaver.jpg" />
        <RigidBody.Dynamic />
    </object>

    <object id="box6" x="50" y="-80" z="50" size="10,10,100">
        <Box3D spriteSource="sprites/beaver.jpg" />
        <RigidBody.Kinematic />
        <SpinningObject _package="pl.AWTGameEngine.custom.performance" />
    </object>

    <object id="vehicle" x="0" y="50" z="0" size="10,10,20">
        <Box3D spriteSource="sprites/beaver.jpg" />
        <Vehicle />
        <Vehicle.Engine peakTorque="1800" maxRPM="12000" idleRPM="1200" />
        <Vehicle.Gearbox gearRatios="-4,0,4,2,1.5,1.1,1,0.8,0.7,0.3" />
        <Vehicle.Wheel />
        <Vehicle.Wheel />
        <Vehicle.Wheel />
        <Vehicle.Wheel />
        <RigidBody.Kinematic />
        <CameraFollow />
        <VehicleSteer _package="pl.AWTGameEngine.custom" />
    </object>

</scene>